{
    "criteria": {
      "requirement": {
        "trigger": "minecraft:player_killed_entity",
        "conditions": {
          "player": {
            "equipment": {
              "mainhand": {
                "items": [
                  "minecraft:crossbow"
                ],
                "nbt": "{sforms:{id:\"shadow_shot_crossbow\"}}"
              }
            }
          }
        }
      }
    },
    "rewards": {
      "function": "sforms:ancient_enchantments/shadow_shot"
    }
  }
  